keras_model_extract/__init__.py
keras_model_extract/keras_model_extract.py
keras_model_extract-0.0.2.dist-info/LICENSE
keras_model_extract-0.0.2.dist-info/METADATA
keras_model_extract-0.0.2.dist-info/WHEEL
keras_model_extract-0.0.2.dist-info/top_level.txt
keras_model_extract-0.0.2.dist-info/RECORD
