Metadata-Version: 2.1
Name: keras-model-extract
Version: 0.0.2
Summary: Utility to extract TensorFlow/Keras model structure and iterate through it
Home-page: https://github.com/nmilosev/keras-model-extract
Author: Nemanja Milosevic
Author-email: nmilosevnm@gmail.com
Project-URL: Bug Tracker, https://github.com/nmilosev/keras-model-extract/issues
Classifier: Programming Language :: Python :: 3
Classifier: License :: OSI Approved :: MIT License
Classifier: Operating System :: OS Independent
Requires-Python: >=3.6
License-File: LICENSE
